mongodbshell/__init__.py
mongodbshell/demo_exists.py
mongodbshell/drop_collection.py
mongodbshell/mongoclient.py
mongodbshell/mping.py
mongodbshell/pager.py
mongodbshell/smping.py
mongodbshell/version.py
mongodbshell-1.1.0b3.dist-info/LICENSE
mongodbshell-1.1.0b3.dist-info/METADATA
mongodbshell-1.1.0b3.dist-info/WHEEL
mongodbshell-1.1.0b3.dist-info/top_level.txt
mongodbshell-1.1.0b3.dist-info/RECORD
