Metadata-Version: 2.1
Name: mongodbshell
Version: 1.1.0b3
Summary: mongodbshell is a class that makes it easy to use MongoDB in the python shell
Home-page: https://github.com/jdrumgoole/mongodbshell
Author: Joe Drumgoole
Author-email: joe@joedrumgoole.com
License: MIT
Platform: UNKNOWN
Classifier: License :: OSI Approved :: MIT License
Classifier: Programming Language :: Python
Classifier: Programming Language :: Python :: 3
Classifier: Programming Language :: Python :: 3.6
Classifier: Programming Language :: Python :: Implementation :: CPython
Classifier: Programming Language :: Python :: Implementation :: PyPy
Requires-Python: >=3.6.0
Requires-Dist: pymongo
Requires-Dist: dnspython
